LICENSE.txt
MANIFEST.in
README.md
setup.py
battleships_game/__init__.py
battleships_game/battleships.txt
battleships_game/components.py
battleships_game/custom_board.JSON
battleships_game/game_engine.py
battleships_game/main.py
battleships_game/mp_game_engine.py
battleships_game/htmlcov/status.json
battleships_game/templates/battleships.txt
battleships_game/templates/placement.json
battleships_game/tests/__init__.py
battleships_game/tests/battleships.txt
battleships_game/tests/custom_board.JSON
battleships_game/tests/decode_error.JSON
battleships_game/tests/error_custom_board.JSON
battleships_game/tests/invalid_data.txt
battleships_game/tests/test_functionality.py
battleships_game/tests/test_helper_functions.py
battleships_game/tests/test_report.txt
battleships_game/tests/test_students.py
battleships_game_pkg_oj263.egg-info/PKG-INFO
battleships_game_pkg_oj263.egg-info/SOURCES.txt
battleships_game_pkg_oj263.egg-info/dependency_links.txt
battleships_game_pkg_oj263.egg-info/top_level.txt