Metadata-Version: 2.1
Name: battleships-game-pkg-oj263
Version: 0.0.7
Summary: A battleships game
Home-page: https://github.com/ollyjohnson/battleships
Author: OJ
Author-email: oj263@exeter.ac.uk
Classifier: Programming Language :: Python :: 3
Classifier: License :: OSI Approved :: MIT License
Classifier: Operating System :: OS Independent
Requires-Python: >=3.11
License-File: LICENSE.txt
